forest/__init__.py
forest/__main__.py
forest/forest.bash
forest/main.py
forest/cmake_tools/__init__.py
forest/cmake_tools/_impl.py
forest/cmake_tools/template/find_package.txt
forest/common/__init__.py
forest/common/build_handler.py
forest/common/config_handler.py
forest/common/eval_handler.py
forest/common/fetch_handler.py
forest/common/forest_dirs.py
forest/common/install.py
forest/common/package.py
forest/common/parser.py
forest/common/print_utils.py
forest/common/proc_utils.py
forest/common/recipe.py
forest/common/setup.bash
forest/common/sudo_refresh.py
forest/git_tools/__init__.py
forest/git_tools/_impl.py
hhcm_forest-1.1.20.data/data/share/bash-completion/completions/forest.bash
hhcm_forest-1.1.20.dist-info/licenses/LICENSE
hhcm_forest-1.1.20.dist-info/METADATA
hhcm_forest-1.1.20.dist-info/WHEEL
hhcm_forest-1.1.20.dist-info/entry_points.txt
hhcm_forest-1.1.20.dist-info/top_level.txt
hhcm_forest-1.1.20.dist-info/RECORD
