Metadata-Version: 2.4
Name: hhcm_forest
Version: 1.1.20
Summary: A minimalistic tool to automate source code cloning and building
Home-page: https://none
Author: Arturo Laurenzi
Author-email: arturo.laurenzi@iit.it
Project-URL: Bug Tracker, https://none
Classifier: Programming Language :: Python :: 3
Classifier: License :: OSI Approved :: MIT License
Classifier: Operating System :: OS Independent
Requires-Python: >=3.6
License-File: LICENSE
Requires-Dist: argcomplete
Requires-Dist: parse
Requires-Dist: pyyaml
Requires-Dist: psutil
Requires-Dist: progressbar
Dynamic: license-file
